Workbook

Sheet dim_customers
A1: customer_id | B1: signup_date | C1: customer_segment | D1: city_tier | E1: lifetime_rewards_tier
A2: CUST_00001 | B2: 45985 | C2: Value Hunter | D2: Tier-2 Emerging | E2: Bronze
A3: CUST_00002 | B3: 45715 | C3: Bulk Buyer | D3: Tier-1 Metro | E3: Bronze
A4: CUST_00003 | B4: 45670 | C4: Premium Organic | D4: Tier-1 Metro | E4: Bronze
A5: CUST_00004 | B5: 45798 | C5: Convenience Seeker | D5: Tier-1 Metro | E5: Bronze
A6: CUST_00005 | B6: 45783 | C6: Value Hunter | D6: Tier-1 Metro | E6: Silver
A7: CUST_00006 | B7: 45772 | C7: Value Hunter | D7: Tier-2 Emerging | E7: Silver
A8: CUST_00007 | B8: 45729 | C8: Value Hunter | D8: Tier-1 Metro | E8: Bronze
A9: CUST_00008 | B9: 45710 | C9: Premium Organic | D9: Tier-1 Metro | E9: Bronze
A10: CUST_00009 | B10: 46004 | C10: Convenience Seeker | D10: Tier-1 Metro | E10: Platinum
A11: CUST_00010 | B11: 45937 | C11: Premium Organic | D11: Tier-2 Emerging | E11: Bronze
A12: CUST_00011 | B12: 45702 | C12: Value Hunter | D12: Tier-1 Metro | E12: Silver
A13: CUST_00012 | B13: 45960 | C13: Bulk Buyer | D13: Tier-1 Metro | E13: Bronze
... A1201: CUST_01200 | B1201: 45831 | C1201: Value Hunter | D1201: Tier-1 Metro | E1201: Silver

Sheet dim_darkstores
A1: hub_id | B1: hub_name | C1: city | D1: daily_operating_cost | E1: target_sla_minutes
A2: HUB_01 | B2: Indiranagar Express | C2: Bangalore | D2: 32000 | E2: 15
A3: HUB_02 | B3: Koramangala Darkstore | C3: Bangalore | D3: 35000 | E3: 15
A4: HUB_03 | B4: Whitefield Hub | C4: Bangalore | D4: 28000 | E4: 20
A5: HUB_04 | B5: Bandra Core | C5: Mumbai | D5: 42000 | E5: 15
A6: HUB_05 | B6: Andheri Logistics | C6: Mumbai | D6: 39000 | E6: 20
A7: HUB_06 | B7: Powai Fulfillment | C7: Mumbai | D7: 31000 | E7: 20
A8: HUB_07 | B8: Gurugram Sector-29 | C8: Delhi NCR | D8: 36000 | E8: 15
A9: HUB_08 | B9: Noida Hub 18 | C9: Delhi NCR | D9: 29000 | E9: 20
A10: HUB_09 | B10: South Ex Express | C10: Delhi NCR | D10: 33000 | E10: 15
A11: HUB_10 | B11: Hitec City Depot | C11: Hyderabad | D11: 30000 | E11: 15
A12: HUB_11 | B12: Gachibowli Logistics | C12: Hyderabad | D12: 27000 | E12: 20
A13: HUB_12 | B13: Kothrud Express | C13: Pune | D13: 24000 | E13: 20
... A16: HUB_15 | B16: Salt Lake Terminal | C16: Kolkata | D16: 25000 | E16: 20

Sheet dim_products
A1: product_id | B1: product_name | C1: category | D1: unit_cost | E1: listing_price
A2: SKU_0001 | B2: Personal Care 1 | C2: Personal Care | D2: 422.07 | E2: 653.68
A3: SKU_0002 | B3: Frozen Food 2 | C3: Instant & Frozen Foods | D3: 71.69 | E3: 93.09
A4: SKU_0003 | B4: Personal Care 3 | C4: Personal Care | D4: 452.99 | E4: 732.4
A5: SKU_0004 | B5: Beverage Snack 4 | C5: Snacks & Beverages | D5: 172.66 | E5: 253.7
A6: SKU_0005 | B6: Home Clean 5 | C6: Household & Cleaning | D6: 406.1 | E6: 607.19
A7: SKU_0006 | B7: Personal Care 6 | C7: Personal Care | D7: 372.31 | E7: 617.56
A8: SKU_0007 | B8: Staples Pack 7 | C8: Staples & Grains | D8: 260.77 | E8: 303.05
A9: SKU_0008 | B9: Beverage Snack 8 | C9: Snacks & Beverages | D9: 65.98 | E9: 87.73
A10: SKU_0009 | B10: Staples Pack 9 | C10: Staples & Grains | D10: 149.59 | E10: 179.12
A11: SKU_0010 | B11: Home Clean 10 | C11: Household & Cleaning | D11: 356.54 | E11: 563.89
A12: SKU_0011 | B12: Personal Care 11 | C12: Personal Care | D12: 105.81 | E12: 151.65
A13: SKU_0012 | B13: Dairy Baked 12 | C13: Dairy & Bakery | D13: 92.38 | E13: 102.02
... A251: SKU_0250 | B251: Dairy Baked 250 | C251: Dairy & Bakery | D251: 201.36 | E251: 228.56

Sheet fact_orders
A1: order_id | B1: customer_id | C1: product_id | D1: hub_id | E1: order_timestamp | F1: delivered_timestamp | G1: order_status | H1: quantity | I1: gross_sales | J1: item_cost | K1: promo_discount | L1: delivery_fee_charged | M1: actual_delivery_cost | N1: payment_gateway_fee | O1: payment_method | P1: sla_delay_minutes | Q1: customer_rating | R1: net_sales | S1: cm1_gross_margin | T1: net_logistics_cost | U1: cm2_variable_profit | V1: cm2_margin_pct | W1: is_profitable_order
A2: ORD_000001 | B2: CUST_00162 | C2: SKU_0238 | D2: HUB_02 | E2: 45658.296 | F2: 45658.305 | G2: DELIVERED | H2: 3 | I2: 2801.34 | J2: 2549.94 | K2: 700.34 | L2: 0 | M2: 48.96 | N2: 37.82 | O2: Cash on Delivery | P2: 0 | Q2: 5 | R2: =I2-K2 -> 2101 | S2: =R2-J2 -> -448.94 | T2: =L2-M2 -> -48.96 | U2: =S2+T2-N2 -> -535.72 | V2: =IF(R2>0, U2/R2, 0) -> -0.25498334 | W2: =IF(U2>0, 1, 0) -> 0
A3: ORD_000002 | B3: CUST_00351 | C3: SKU_0010 | D3: HUB_03 | E3: 45658.486 | F3: 45658.5 | G3: DELIVERED | H3: 1 | I3: 563.89 | J3: 356.54 | K3: 84.58 | L3: 0 | M3: 58.86 | N3: 8.63 | O3: Debit Card | P3: 0 | Q3: 5 | R3: =I3-K3 -> 479.31 | S3: =R3-J3 -> 122.77 | T3: =L3-M3 -> -58.86 | U3: =S3+T3-N3 -> 55.28 | V3: =IF(R3>0, U3/R3, 0) -> 0.11533246 | W3: =IF(U3>0, 1, 0) -> 1
A4: ORD_000003 | B4: CUST_00434 | C4: SKU_0152 | D4: HUB_08 | E4: 45658.502 | F4: 45658.512 | G4: DELIVERED | H4: 2 | I4: 912.82 | J4: 638.92 | K4: 45.64 | L4: 0 | M4: 61.96 | N4: 15.61 | O4: UPI | P4: 0 | Q4: 5 | R4: =I4-K4 -> 867.18 | S4: =R4-J4 -> 228.26 | T4: =L4-M4 -> -61.96 | U4: =S4+T4-N4 -> 150.69 | V4: =IF(R4>0, U4/R4, 0) -> 0.17377015 | W4: =IF(U4>0, 1, 0) -> 1
A5: ORD_000004 | B5: CUST_00852 | C5: SKU_0061 | D5: HUB_03 | E5: 45658.716 | F5: 45658.727 | G5: DELIVERED | H5: 1 | I5: 235.64 | J5: 162.24 | K5: 0 | L5: 30 | M5: 51.85 | N5: 4.78 | O5: UPI | P5: 0 | Q5: 4 | R5: =I5-K5 -> 235.64 | S5: =R5-J5 -> 73.4 | T5: =L5-M5 -> -21.85 | U5: =S5+T5-N5 -> 46.77 | V5: =IF(R5>0, U5/R5, 0) -> 0.19848073 | W5: =IF(U5>0, 1, 0) -> 1
A6: ORD_000005 | B6: CUST_00140 | C6: SKU_0238 | D6: HUB_07 | E6: 45658.784 | F6: 45658.789 | G6: DELIVERED | H6: 1 | I6: 933.78 | J6: 849.98 | K6: 140.07 | L6: 0 | M6: 46.57 | N6: 14.29 | O6: UPI | P6: 0 | Q6: 5 | R6: =I6-K6 -> 793.71 | S6: =R6-J6 -> -56.27 | T6: =L6-M6 -> -46.57 | U6: =S6+T6-N6 -> -117.13 | V6: =IF(R6>0, U6/R6, 0) -> -0.14757279 | W6: =IF(U6>0, 1, 0) -> 0
A7: ORD_000006 | B7: CUST_01156 | C7: SKU_0018 | D7: HUB_10 | E7: 45658.801 | F7: 45658.809 | G7: DELIVERED | H7: 1 | I7: 72.87 | J7: 55.17 | K7: 0 | L7: 30 | M7: 53.05 | N7: 1.85 | O7: UPI | P7: 0 | Q7: 5 | R7: =I7-K7 -> 72.87 | S7: =R7-J7 -> 17.7 | T7: =L7-M7 -> -23.05 | U7: =S7+T7-N7 -> -7.2 | V7: =IF(R7>0, U7/R7, 0) -> -0.098806093 | W7: =IF(U7>0, 1, 0) -> 0
A8: ORD_000007 | B8: CUST_00087 | C8: SKU_0086 | D8: HUB_14 | E8: 45658.824 | F8: 45658.841 | G8: RETURNED | H8: 1 | I8: 289.4 | J8: 173.32 | K8: 28.94 | L8: 30 | M8: 50.82 | N8: 5.23 | O8: UPI | P8: 9 | Q8: 1 | R8: =I8-K8 -> 260.46 | S8: =R8-J8 -> 87.14 | T8: =L8-M8 -> -20.82 | U8: =S8+T8-N8 -> 61.09 | V8: =IF(R8>0, U8/R8, 0) -> 0.23454657 | W8: =IF(U8>0, 1, 0) -> 1
A9: ORD_000008 | B9: CUST_00183 | C9: SKU_0137 | D9: HUB_10 | E9: 45658.826 | F9: 45658.847 | G9: DELIVERED | H9: 2 | I9: 327.6 | J9: 266.98 | K9: 32.76 | L9: 30 | M9: 38.09 | N9: 5.85 | O9: Cash on Delivery | P9: 16 | Q9: 2 | R9: =I9-K9 -> 294.84 | S9: =R9-J9 -> 27.86 | T9: =L9-M9 -> -8.09 | U9: =S9+T9-N9 -> 13.92 | V9: =IF(R9>0, U9/R9, 0) -> 0.047212047 | W9: =IF(U9>0, 1, 0) -> 1
A10: ORD_000009 | B10: CUST_00368 | C10: SKU_0145 | D10: HUB_09 | E10: 45658.839 | F10: 45658.855 | G10: DELIVERED | H10: 1 | I10: 21.98 | J10: 18.04 | K10: 3.3 | L10: 30 | M10: 43.34 | N10: 0.88 | O10: UPI | P10: 9 | Q10: 3 | R10: =I10-K10 -> 18.68 | S10: =R10-J10 -> 0.64 | T10: =L10-M10 -> -13.34 | U10: =S10+T10-N10 -> -13.58 | V10: =IF(R10>0, U10/R10, 0) -> -0.72698073 | W10: =IF(U10>0, 1, 0) -> 0
A11: ORD_000010 | B11: CUST_00129 | C11: SKU_0230 | D11: HUB_13 | E11: 45658.876 | F11: 45658.892 | G11: DELIVERED | H11: 4 | I11: 2630.6 | J11: 1737.24 | K11: 131.53 | L11: 0 | M11: 53.24 | N11: 44.98 | O11: Credit Card | P11: 3 | Q11: 4 | R11: =I11-K11 -> 2499.07 | S11: =R11-J11 -> 761.83 | T11: =L11-M11 -> -53.24 | U11: =S11+T11-N11 -> 663.61 | V11: =IF(R11>0, U11/R11, 0) -> 0.26554278 | W11: =IF(U11>0, 1, 0) -> 1
A12: ORD_000011 | B12: CUST_00670 | C12: SKU_0128 | D12: HUB_08 | E12: 45658.93 | F12: 45658.944 | G12: RETURNED | H12: 2 | I12: 1015.48 | J12: 700.78 | K12: 101.55 | L12: 0 | M12: 61.5 | N12: 16.45 | O12: Credit Card | P12: 0 | Q12: 1 | R12: =I12-K12 -> 913.93 | S12: =R12-J12 -> 213.15 | T12: =L12-M12 -> -61.5 | U12: =S12+T12-N12 -> 135.2 | V12: =IF(R12>0, U12/R12, 0) -> 0.14793256 | W12: =IF(U12>0, 1, 0) -> 1
A13: ORD_000012 | B13: CUST_00149 | C13: SKU_0104 | D13: HUB_01 | E13: 45658.942 | F13: 45658.948 | G13: DELIVERED | H13: 2 | I13: 150.58 | J13: 124.92 | K13: 22.59 | L13: 30 | M13: 60.8 | N13: 2.84 | O13: UPI | P13: 0 | Q13: 5 | R13: =I13-K13 -> 127.99 | S13: =R13-J13 -> 3.07 | T13: =L13-M13 -> -30.8 | U13: =S13+T13-N13 -> -30.57 | V13: =IF(R13>0, U13/R13, 0) -> -0.23884678 | W13: =IF(U13>0, 1, 0) -> 0
... A24: ORD_000023 | B24: CUST_00975 | C24: SKU_0025 | D24: HUB_06 | E24: 45659.735 | F24: 45659.746 | G24: DELIVERED | H24: 1 | I24: 241.16 | J24: 178.02 | K24: 12.06 | L24: 30 | M24: 47.64 | N24: 4.66 | O24: UPI | P24: 0 | Q24: 5 | R24: =I24-K24 -> 229.1 | S24: =R24-J24 -> 51.08 | T24: =L24-M24 -> -17.64 | U24: =S24+T24-N24 -> 28.78 | V24: =IF(R24>0, U24/R24, 0) -> 0.125622 | W24: =IF(U24>0, 1, 0) -> 1
A25: ORD_000024 | B25: CUST_01049 | C25: SKU_0139 | D25: HUB_01 | E25: 45659.816 | G25: CANCELLED | H25: 2 | I25: 375.14 | J25: 336.92 | K25: 56.27 | L25: 30 | M25: 38.72 | N25: 0 | O25: UPI | P25: 11 | R25: =I25-K25 -> 318.87 | S25: =R25-J25 -> -18.05 | T25: =L25-M25 -> -8.72 | U25: =S25+T25-N25 -> -26.77 | V25: =IF(R25>0, U25/R25, 0) -> -0.083952708 | W25: =IF(U25>0, 1, 0) -> 0
A26: ORD_000025 | B26: CUST_00789 | C26: SKU_0044 | D26: HUB_13 | E26: 45659.824 | F26: 45659.839 | G26: DELIVERED | H26: 4 | I26: 399.6 | J26: 260.76 | K26: 0 | L26: 0 | M26: 40.13 | N26: 7.19 | O26: UPI | P26: 2 | Q26: 4 | R26: =I26-K26 -> 399.6 | S26: =R26-J26 -> 138.84 | T26: =L26-M26 -> -40.13 | U26: =S26+T26-N26 -> 91.52 | V26: =IF(R26>0, U26/R26, 0) -> 0.22902903 | W26: =IF(U26>0, 1, 0) -> 1
A27: ORD_000026 | B27: CUST_00984 | C27: SKU_0014 | D27: HUB_15 | E27: 45659.904 | F27: 45659.918 | G27: DELIVERED | H27: 1 | I27: 294.16 | J27: 199.8 | K27: 44.12 | L27: 30 | M27: 44.81 | N27: 5.04 | O27: UPI | P27: 0 | Q27: 5 | R27: =I27-K27 -> 250.04 | S27: =R27-J27 -> 50.24 | T27: =L27-M27 -> -14.81 | U27: =S27+T27-N27 -> 30.39 | V27: =IF(R27>0, U27/R27, 0) -> 0.12154055 | W27: =IF(U27>0, 1, 0) -> 1
A28: ORD_000027 | B28: CUST_00889 | C28: SKU_0237 | D28: HUB_06 | E28: 45660.37 | F28: 45660.385 | G28: DELIVERED | H28: 1 | I28: 738.97 | J28: 669.94 | K28: 0 | L28: 0 | M28: 46.49 | N28: 13.3 | O28: Debit Card | P28: 1 | Q28: 4 | R28: =I28-K28 -> 738.97 | S28: =R28-J28 -> 69.03 | T28: =L28-M28 -> -46.49 | U28: =S28+T28-N28 -> 9.24 | V28: =IF(R28>0, U28/R28, 0) -> 0.012503891 | W28: =IF(U28>0, 1, 0) -> 1
A29: ORD_000028 | B29: CUST_00890 | C29: SKU_0029 | D29: HUB_14 | E29: 45660.448 | F29: 45660.457 | G29: DELIVERED | H29: 1 | I29: 147.56 | J29: 101.59 | K29: 0 | L29: 30 | M29: 52.29 | N29: 3.2 | O29: UPI | P29: 0 | Q29: 4 | R29: =I29-K29 -> 147.56 | S29: =R29-J29 -> 45.97 | T29: =L29-M29 -> -22.29 | U29: =S29+T29-N29 -> 20.48 | V29: =IF(R29>0, U29/R29, 0) -> 0.138791 | W29: =IF(U29>0, 1, 0) -> 1
A30: ORD_000029 | B30: CUST_00070 | C30: SKU_0074 | D30: HUB_04 | E30: 45660.486 | F30: 45660.499 | G30: DELIVERED | H30: 1 | I30: 269.53 | J30: 195.85 | K30: 40.43 | L30: 30 | M30: 43.55 | N30: 4.66 | O30: Credit Card | P30: 4 | Q30: 3 | R30: =I30-K30 -> 229.1 | S30: =R30-J30 -> 33.25 | T30: =L30-M30 -> -13.55 | U30: =S30+T30-N30 -> 15.04 | V30: =IF(R30>0, U30/R30, 0) -> 0.065648189 | W30: =IF(U30>0, 1, 0) -> 1
A31: ORD_000030 | B31: CUST_00625 | C31: SKU_0050 | D31: HUB_04 | E31: 45660.5 | F31: 45660.513 | G31: DELIVERED | H31: 1 | I31: 76.73 | J31: 62.02 | K31: 11.51 | L31: 30 | M31: 54.31 | N31: 1.71 | O31: Credit Card | P31: 4 | Q31: 3 | R31: =I31-K31 -> 65.22 | S31: =R31-J31 -> 3.2 | T31: =L31-M31 -> -24.31 | U31: =S31+T31-N31 -> -22.82 | V31: =IF(R31>0, U31/R31, 0) -> -0.34989267 | W31: =IF(U31>0, 1, 0) -> 0
A32: ORD_000031 | B32: CUST_00875 | C32: SKU_0240 | D32: HUB_14 | E32: 45660.515 | F32: 45660.521 | G32: DELIVERED | H32: 3 | I32: 1617.3 | J32: 1412.76 | K32: 161.73 | L32: 0 | M32: 60.68 | N32: 26.2 | O32: Debit Card | P32: 0 | Q32: 5 | R32: =I32-K32 -> 1455.57 | S32: =R32-J32 -> 42.81 | T32: =L32-M32 -> -60.68 | U32: =S32+T32-N32 -> -44.07 | V32: =IF(R32>0, U32/R32, 0) -> -0.030276799 | W32: =IF(U32>0, 1, 0) -> 0
A33: ORD_000032 | B33: CUST_01136 | C33: SKU_0005 | D33: HUB_02 | E33: 45660.522 | F33: 45660.534 | G33: DELIVERED | H33: 3 | I33: 1821.57 | J33: 1218.3 | K33: 455.39 | L33: 0 | M33: 64.64 | N33: 24.59 | O33: Cash on Delivery | P33: 2 | Q33: 4 | R33: =I33-K33 -> 1366.18 | S33: =R33-J33 -> 147.88 | T33: =L33-M33 -> -64.64 | U33: =S33+T33-N33 -> 58.65 | V33: =IF(R33>0, U33/R33, 0) -> 0.042929921 | W33: =IF(U33>0, 1, 0) -> 1
A34: ORD_000033 | B34: CUST_00471 | C34: SKU_0200 | D34: HUB_13 | E34: 45660.547 | F34: 45660.567 | G34: DELIVERED | H34: 2 | I34: 1595.64 | J34: 1386.34 | K34: 159.56 | L34: 0 | M34: 62.35 | N34: 25.85 | O34: UPI | P34: 9 | Q34: 3 | R34: =I34-K34 -> 1436.08 | S34: =R34-J34 -> 49.74 | T34: =L34-M34 -> -62.35 | U34: =S34+T34-N34 -> -38.46 | V34: =IF(R34>0, U34/R34, 0) -> -0.026781238 | W34: =IF(U34>0, 1, 0) -> 0
A35: ORD_000034 | B35: CUST_00091 | C35: SKU_0110 | D35: HUB_11 | E35: 45660.567 | F35: 45660.588 | G35: DELIVERED | H35: 1 | I35: 111.9 | J35: 79.15 | K35: 0 | L35: 30 | M35: 43.53 | N35: 2.55 | O35: Net Banking | P35: 10 | Q35: 3 | R35: =I35-K35 -> 111.9 | S35: =R35-J35 -> 32.75 | T35: =L35-M35 -> -13.53 | U35: =S35+T35-N35 -> 16.67 | V35: =IF(R35>0, U35/R35, 0) -> 0.1489723 | W35: =IF(U35>0, 1, 0) -> 1
A36: ORD_000035 | B36: CUST_00530 | C36: SKU_0197 | D36: HUB_14 | E36: 45660.594 | F36: 45660.607 | G36: DELIVERED | H36: 3 | I36: 614.13 | J36: 411.81 | K36: 30.71 | L36: 0 | M36: 60.25 | N36: 10.5 | O36: UPI | P36: 4 | Q36: 4 | R36: =I36-K36 -> 583.42 | S36: =R36-J36 -> 171.61 | T36: =L36-M36 -> -60.25 | U36: =S36+T36-N36 -> 100.86 | V36: =IF(R36>0, U36/R36, 0) -> 0.17287717 | W36: =IF(U36>0, 1, 0) -> 1
A37: ORD_000036 | B37: CUST_00661 | C37: SKU_0122 | D37: HUB_04 | E37: 45660.649 | F37: 45660.655 | G37: DELIVERED | H37: 2 | I37: 1617.58 | J37: 1434.22 | K37: 80.88 | L37: 0 | M37: 47.08 | N37: 27.66 | O37: Debit Card | P37: 0 | Q37: 5 | R37: =I37-K37 -> 1536.7 | S37: =R37-J37 -> 102.48 | T37: =L37-M37 -> -47.08 | U37: =S37+T37-N37 -> 27.74 | V37: =IF(R37>0, U37/R37, 0) -> 0.018051669 | W37: =IF(U37>0, 1, 0) -> 1
... A73: ORD_000072 | B73: CUST_00857 | C73: SKU_0191 | D73: HUB_06 | E73: 45662.643 | F73: 45662.654 | G73: DELIVERED | H73: 2 | I73: 383.66 | J73: 239.24 | K73: 0 | L73: 30 | M73: 63.02 | N73: 7.45 | O73: UPI | P73: 0 | Q73: 5 | R73: =I73-K73 -> 383.66 | S73: =R73-J73 -> 144.42 | T73: =L73-M73 -> -33.02 | U73: =S73+T73-N73 -> 103.95 | V73: =IF(R73>0, U73/R73, 0) -> 0.27094302 | W73: =IF(U73>0, 1, 0) -> 1
A74: ORD_000073 | B74: CUST_00897 | C74: SKU_0042 | D74: HUB_08 | E74: 45662.658 | G74: CANCELLED | H74: 2 | I74: 211.66 | J74: 152.46 | K74: 31.75 | L74: 30 | M74: 61.04 | N74: 0 | O74: Credit Card | P74: 11 | R74: =I74-K74 -> 179.91 | S74: =R74-J74 -> 27.45 | T74: =L74-M74 -> -31.04 | U74: =S74+T74-N74 -> -3.59 | V74: =IF(R74>0, U74/R74, 0) -> -0.019954422 | W74: =IF(U74>0, 1, 0) -> 0
A75: ORD_000074 | B75: CUST_00278 | C75: SKU_0064 | D75: HUB_15 | E75: 45662.76 | F75: 45662.774 | G75: DELIVERED | H75: 1 | I75: 204.1 | J75: 164.4 | K75: 30.62 | L75: 30 | M75: 42.79 | N75: 3.66 | O75: UPI | P75: 0 | Q75: 5 | R75: =I75-K75 -> 173.48 | S75: =R75-J75 -> 9.08 | T75: =L75-M75 -> -12.79 | U75: =S75+T75-N75 -> -7.37 | V75: =IF(R75>0, U75/R75, 0) -> -0.042483283 | W75: =IF(U75>0, 1, 0) -> 0
A76: ORD_000075 | B76: CUST_00552 | C76: SKU_0182 | D76: HUB_13 | E76: 45662.778 | F76: 45662.796 | G76: RETURNED | H76: 1 | I76: 423.08 | J76: 388.35 | K76: 21.15 | L76: 0 | M76: 58.55 | N76: 7.23 | O76: UPI | P76: 7 | Q76: 1 | R76: =I76-K76 -> 401.93 | S76: =R76-J76 -> 13.58 | T76: =L76-M76 -> -58.55 | U76: =S76+T76-N76 -> -52.2 | V76: =IF(R76>0, U76/R76, 0) -> -0.12987336 | W76: =IF(U76>0, 1, 0) -> 0
A77: ORD_000076 | B77: CUST_00111 | C77: SKU_0078 | D77: HUB_07 | E77: 45662.782 | F77: 45662.795 | G77: DELIVERED | H77: 1 | I77: 58.68 | J77: 44.37 | K77: 5.87 | L77: 30 | M77: 38.32 | N77: 1.49 | O77: UPI | P77: 4 | Q77: 3 | R77: =I77-K77 -> 52.81 | S77: =R77-J77 -> 8.44 | T77: =L77-M77 -> -8.32 | U77: =S77+T77-N77 -> -1.37 | V77: =IF(R77>0, U77/R77, 0) -> -0.025942056 | W77: =IF(U77>0, 1, 0) -> 0
A78: ORD_000077 | B78: CUST_00385 | C78: SKU_0127 | D78: HUB_03 | E78: 45662.831 | F78: 45662.843 | G78: DELIVERED | H78: 1 | I78: 30.14 | J78: 23.96 | K78: 4.52 | L78: 30 | M78: 63.41 | N78: 1 | O78: Net Banking | P78: 0 | Q78: 5 | R78: =I78-K78 -> 25.62 | S78: =R78-J78 -> 1.66 | T78: =L78-M78 -> -33.41 | U78: =S78+T78-N78 -> -32.75 | V78: =IF(R78>0, U78/R78, 0) -> -1.2782982 | W78: =IF(U78>0, 1, 0) -> 0
A79: ORD_000078 | B79: CUST_00761 | C79: SKU_0205 | D79: HUB_08 | E79: 45662.85 | F79: 45662.874 | G79: DELIVERED | H79: 1 | I79: 172.15 | J79: 149.53 | K79: 8.61 | L79: 30 | M79: 37.25 | N79: 3.48 | O79: UPI | P79: 14 | Q79: 3 | R79: =I79-K79 -> 163.54 | S79: =R79-J79 -> 14.01 | T79: =L79-M79 -> -7.25 | U79: =S79+T79-N79 -> 3.28 | V79: =IF(R79>0, U79/R79, 0) -> 0.020056255 | W79: =IF(U79>0, 1, 0) -> 1
A80: ORD_000079 | B80: CUST_00694 | C80: SKU_0105 | D80: HUB_10 | E80: 45662.94 | F80: 45662.953 | G80: DELIVERED | H80: 3 | I80: 534.51 | J80: 355.26 | K80: 80.18 | L80: 0 | M80: 44.88 | N80: 8.18 | O80: Debit Card | P80: 4 | Q80: 4 | R80: =I80-K80 -> 454.33 | S80: =R80-J80 -> 99.07 | T80: =L80-M80 -> -44.88 | U80: =S80+T80-N80 -> 46.01 | V80: =IF(R80>0, U80/R80, 0) -> 0.10127 | W80: =IF(U80>0, 1, 0) -> 1
A81: ORD_000080 | B81: CUST_00405 | C81: SKU_0199 | D81: HUB_01 | E81: 45663.25 | F81: 45663.263 | G81: DELIVERED | H81: 1 | I81: 547.51 | J81: 328.7 | K81: 54.75 | L81: 0 | M81: 53.38 | N81: 8.87 | O81: UPI | P81: 3 | Q81: 3 | R81: =I81-K81 -> 492.76 | S81: =R81-J81 -> 164.06 | T81: =L81-M81 -> -53.38 | U81: =S81+T81-N81 -> 101.81 | V81: =IF(R81>0, U81/R81, 0) -> 0.20661174 | W81: =IF(U81>0, 1, 0) -> 1
A82: ORD_000081 | B82: CUST_00022 | C82: SKU_0076 | D82: HUB_01 | E82: 45663.306 | F82: 45663.314 | G82: DELIVERED | H82: 5 | I82: 569 | J82: 418.85 | K82: 28.45 | L82: 0 | M82: 59.37 | N82: 9.73 | O82: UPI | P82: 0 | Q82: 5 | R82: =I82-K82 -> 540.55 | S82: =R82-J82 -> 121.7 | T82: =L82-M82 -> -59.37 | U82: =S82+T82-N82 -> 52.6 | V82: =IF(R82>0, U82/R82, 0) -> 0.097308297 | W82: =IF(U82>0, 1, 0) -> 1
A83: ORD_000082 | B83: CUST_00678 | C83: SKU_0165 | D83: HUB_13 | E83: 45663.38 | F83: 45663.403 | G83: DELIVERED | H83: 1 | I83: 234.49 | J83: 139.73 | K83: 0 | L83: 30 | M83: 43.1 | N83: 4.76 | O83: UPI | P83: 13 | Q83: 2 | R83: =I83-K83 -> 234.49 | S83: =R83-J83 -> 94.76 | T83: =L83-M83 -> -13.1 | U83: =S83+T83-N83 -> 76.9 | V83: =IF(R83>0, U83/R83, 0) -> 0.32794575 | W83: =IF(U83>0, 1, 0) -> 1
A84: ORD_000083 | B84: CUST_00611 | C84: SKU_0242 | D84: HUB_13 | E84: 45663.403 | F84: 45663.42 | G84: DELIVERED | H84: 3 | I84: 2096.64 | J84: 1769.07 | K84: 209.66 | L84: 0 | M84: 40.11 | N84: 33.97 | O84: Debit Card | P84: 4 | Q84: 4 | R84: =I84-K84 -> 1886.98 | S84: =R84-J84 -> 117.91 | T84: =L84-M84 -> -40.11 | U84: =S84+T84-N84 -> 43.83 | V84: =IF(R84>0, U84/R84, 0) -> 0.023227591 | W84: =IF(U84>0, 1, 0) -> 1
A85: ORD_000084 | B85: CUST_00008 | C85: SKU_0132 | D85: HUB_10 | E85: 45663.448 | F85: 45663.464 | G85: DELIVERED | H85: 2 | I85: 1795.8 | J85: 1505.36 | K85: 448.95 | L85: 0 | M85: 39.13 | N85: 24.24 | O85: Credit Card | P85: 7 | Q85: 3 | R85: =I85-K85 -> 1346.85 | S85: =R85-J85 -> -158.51 | T85: =L85-M85 -> -39.13 | U85: =S85+T85-N85 -> -221.88 | V85: =IF(R85>0, U85/R85, 0) -> -0.16473995 | W85: =IF(U85>0, 1, 0) -> 0
A86: ORD_000085 | B86: CUST_00702 | C86: SKU_0130 | D86: HUB_13 | E86: 45663.451 | F86: 45663.473 | G86: DELIVERED | H86: 1 | I86: 148.98 | J86: 115.45 | K86: 0 | L86: 30 | M86: 48.82 | N86: 3.22 | O86: Credit Card | P86: 11 | Q86: 1 | R86: =I86-K86 -> 148.98 | S86: =R86-J86 -> 33.53 | T86: =L86-M86 -> -18.82 | U86: =S86+T86-N86 -> 11.49 | V86: =IF(R86>0, U86/R86, 0) -> 0.077124446 | W86: =IF(U86>0, 1, 0) -> 1
... A88: ORD_000087 | B88: CUST_00602 | C88: SKU_0122 | D88: HUB_13 | E88: 45663.594 | F88: 45663.623 | G88: DELIVERED | H88: 2 | I88: 1617.58 | J88: 1434.22 | K88: 161.76 | L88: 0 | M88: 60.86 | N88: 26.2 | O88: Credit Card | P88: 22 | Q88: 3 | R88: =I88-K88 -> 1455.82 | S88: =R88-J88 -> 21.6 | T88: =L88-M88 -> -60.86 | U88: =S88+T88-N88 -> -65.46 | V88: =IF(R88>0, U88/R88, 0) -> -0.04496435 | W88: =IF(U88>0, 1, 0) -> 0
A89: ORD_000088 | B89: CUST_00657 | C89: SKU_0044 | D89: HUB_09 | E89: 45663.675 | G89: CANCELLED | H89: 3 | I89: 299.7 | J89: 195.57 | K89: 74.92 | L89: 30 | M89: 57.59 | N89: 0 | O89: UPI | P89: 0 | R89: =I89-K89 -> 224.78 | S89: =R89-J89 -> 29.21 | T89: =L89-M89 -> -27.59 | U89: =S89+T89-N89 -> 1.62 | V89: =IF(R89>0, U89/R89, 0) -> 0.0072070469 | W89: =IF(U89>0, 1, 0) -> 1
A90: ORD_000089 | B90: CUST_00166 | C90: SKU_0195 | D90: HUB_10 | E90: 45663.727 | F90: 45663.739 | G90: DELIVERED | H90: 1 | I90: 118.58 | J90: 86.52 | K90: 29.64 | L90: 30 | M90: 61.63 | N90: 2.14 | O90: UPI | P90: 2 | Q90: 4 | R90: =I90-K90 -> 88.94 | S90: =R90-J90 -> 2.42 | T90: =L90-M90 -> -31.63 | U90: =S90+T90-N90 -> -31.35 | V90: =IF(R90>0, U90/R90, 0) -> -0.35248482 | W90: =IF(U90>0, 1, 0) -> 0
A91: ORD_000090 | B91: CUST_00849 | C91: SKU_0196 | D91: HUB_06 | E91: 45663.731 | F91: 45663.748 | G91: DELIVERED | H91: 1 | I91: 196.03 | J91: 122.88 | K91: 19.6 | L91: 30 | M91: 63.98 | N91: 3.72 | O91: Cash on Delivery | P91: 5 | Q91: 4 | R91: =I91-K91 -> 176.43 | S91: =R91-J91 -> 53.55 | T91: =L91-M91 -> -33.98 | U91: =S91+T91-N91 -> 15.85 | V91: =IF(R91>0, U91/R91, 0) -> 0.089837329 | W91: =IF(U91>0, 1, 0) -> 1
A92: ORD_000091 | B92: CUST_00496 | C92: SKU_0102 | D92: HUB_05 | E92: 45663.736 | F92: 45663.747 | G92: DELIVERED | H92: 1 | I92: 42.45 | J92: 30.17 | K92: 0 | L92: 30 | M92: 47.4 | N92: 1.3 | O92: UPI | P92: 0 | Q92: 5 | R92: =I92-K92 -> 42.45 | S92: =R92-J92 -> 12.28 | T92: =L92-M92 -> -17.4 | U92: =S92+T92-N92 -> -6.42 | V92: =IF(R92>0, U92/R92, 0) -> -0.15123675 | W92: =IF(U92>0, 1, 0) -> 0
A93: ORD_000092 | B93: CUST_00590 | C93: SKU_0204 | D93: HUB_02 | E93: 45663.738 | F93: 45663.755 | G93: DELIVERED | H93: 1 | I93: 799.86 | J93: 435.02 | K93: 39.99 | L93: 0 | M93: 48.4 | N93: 13.68 | O93: Credit Card | P93: 9 | Q93: 3 | R93: =I93-K93 -> 759.87 | S93: =R93-J93 -> 324.85 | T93: =L93-M93 -> -48.4 | U93: =S93+T93-N93 -> 262.77 | V93: =IF(R93>0, U93/R93, 0) -> 0.34580915 | W93: =IF(U93>0, 1, 0) -> 1
A94: ORD_000093 | B94: CUST_00429 | C94: SKU_0211 | D94: HUB_11 | E94: 45663.794 | F94: 45663.81 | G94: DELIVERED | H94: 4 | I94: 1648.08 | J94: 1234.36 | K94: 164.81 | L94: 0 | M94: 38.67 | N94: 26.7 | O94: UPI | P94: 4 | Q94: 3 | R94: =I94-K94 -> 1483.27 | S94: =R94-J94 -> 248.91 | T94: =L94-M94 -> -38.67 | U94: =S94+T94-N94 -> 183.54 | V94: =IF(R94>0, U94/R94, 0) -> 0.12374011 | W94: =IF(U94>0, 1, 0) -> 1
A95: ORD_000094 | B95: CUST_00774 | C95: SKU_0202 | D95: HUB_09 | E95: 45663.794 | F95: 45663.805 | G95: DELIVERED | H95: 2 | I95: 237.18 | J95: 187.76 | K95: 11.86 | L95: 30 | M95: 50.83 | N95: 4.6 | O95: Credit Card | P95: 0 | Q95: 5 | R95: =I95-K95 -> 225.32 | S95: =R95-J95 -> 37.56 | T95: =L95-M95 -> -20.83 | U95: =S95+T95-N95 -> 12.13 | V95: =IF(R95>0, U95/R95, 0) -> 0.053834546 | W95: =IF(U95>0, 1, 0) -> 1
A96: ORD_000095 | B96: CUST_00163 | C96: SKU_0062 | D96: HUB_06 | E96: 45663.824 | G96: CANCELLED | H96: 1 | I96: 101.98 | J96: 82.05 | K96: 10.2 | L96: 30 | M96: 52.34 | N96: 0 | O96: Cash on Delivery | P96: 9 | R96: =I96-K96 -> 91.78 | S96: =R96-J96 -> 9.73 | T96: =L96-M96 -> -22.34 | U96: =S96+T96-N96 -> -12.61 | V96: =IF(R96>0, U96/R96, 0) -> -0.13739377 | W96: =IF(U96>0, 1, 0) -> 0
A97: ORD_000096 | B97: CUST_00366 | C97: SKU_0001 | D97: HUB_08 | E97: 45663.875 | F97: 45663.881 | G97: DELIVERED | H97: 1 | I97: 653.68 | J97: 422.07 | K97: 32.68 | L97: 0 | M97: 54.84 | N97: 11.18 | O97: UPI | P97: 0 | Q97: 4 | R97: =I97-K97 -> 621 | S97: =R97-J97 -> 198.93 | T97: =L97-M97 -> -54.84 | U97: =S97+T97-N97 -> 132.91 | V97: =IF(R97>0, U97/R97, 0) -> 0.21402576 | W97: =IF(U97>0, 1, 0) -> 1
A98: ORD_000097 | B98: CUST_00072 | C98: SKU_0017 | D98: HUB_09 | E98: 45664.263 | F98: 45664.268 | G98: DELIVERED | H98: 1 | I98: 249.73 | J98: 150.92 | K98: 24.97 | L98: 30 | M98: 64.29 | N98: 4.59 | O98: Net Banking | P98: 0 | Q98: 5 | R98: =I98-K98 -> 224.76 | S98: =R98-J98 -> 73.84 | T98: =L98-M98 -> -34.29 | U98: =S98+T98-N98 -> 34.96 | V98: =IF(R98>0, U98/R98, 0) -> 0.15554369 | W98: =IF(U98>0, 1, 0) -> 1
A99: ORD_000098 | B99: CUST_00655 | C99: SKU_0016 | D99: HUB_09 | E99: 45664.342 | F99: 45664.352 | G99: DELIVERED | H99: 3 | I99: 880.65 | J99: 702.27 | K99: 44.03 | L99: 0 | M99: 44.66 | N99: 15.06 | O99: Credit Card | P99: 0 | Q99: 4 | R99: =I99-K99 -> 836.62 | S99: =R99-J99 -> 134.35 | T99: =L99-M99 -> -44.66 | U99: =S99+T99-N99 -> 74.63 | V99: =IF(R99>0, U99/R99, 0) -> 0.089204179 | W99: =IF(U99>0, 1, 0) -> 1
A100: ORD_000099 | B100: CUST_00269 | C100: SKU_0009 | D100: HUB_08 | E100: 45664.38 | F100: 45664.397 | G100: DELIVERED | H100: 4 | I100: 716.48 | J100: 598.36 | K100: 179.12 | L100: 0 | M100: 56.93 | N100: 9.67 | O100: UPI | P100: 4 | Q100: 3 | R100: =I100-K100 -> 537.36 | S100: =R100-J100 -> -61 | T100: =L100-M100 -> -56.93 | U100: =S100+T100-N100 -> -127.6 | V100: =IF(R100>0, U100/R100, 0) -> -0.2374572 | W100: =IF(U100>0, 1, 0) -> 0
A101: ORD_000100 | B101: CUST_00415 | C101: SKU_0249 | D101: HUB_12 | E101: 45664.426 | F101: 45664.444 | G101: DELIVERED | H101: 1 | I101: 178.12 | J101: 117.7 | K101: 26.72 | L101: 30 | M101: 41.77 | N101: 3.27 | O101: UPI | P101: 5 | Q101: 4 | R101: =I101-K101 -> 151.4 | S101: =R101-J101 -> 33.7 | T101: =L101-M101 -> -11.77 | U101: =S101+T101-N101 -> 18.66 | V101: =IF(R101>0, U101/R101, 0) -> 0.12324967 | W101: =IF(U101>0, 1, 0) -> 1
A102: ORD_000101 | B102: CUST_01016 | C102: SKU_0181 | D102: HUB_10 | E102: 45664.435 | F102: 45664.45 | G102: DELIVERED | H102: 1 | I102: 149.33 | J102: 101.29 | K102: 14.93 | L102: 30 | M102: 42.91 | N102: 2.96 | O102: UPI | P102: 6 | Q102: 4 | R102: =I102-K102 -> 134.4 | S102: =R102-J102 -> 33.11 | T102: =L102-M102 -> -12.91 | U102: =S102+T102-N102 -> 17.24 | V102: =IF(R102>0, U102/R102, 0) -> 0.12827381 | W102: =IF(U102>0, 1, 0) -> 1
A103: ORD_000102 | B103: CUST_00675 | C103: SKU_0201 | D103: HUB_08 | E103: 45664.466 | G103: CANCELLED | H103: 4 | I103: 463.08 | J103: 416.76 | K103: 23.15 | L103: 0 | M103: 43.89 | N103: 0 | O103: UPI | P103: 11 | R103: =I103-K103 -> 439.93 | S103: =R103-J103 -> 23.17 | T103: =L103-M103 -> -43.89 | U103: =S103+T103-N103 -> -20.72 | V103: =IF(R103>0, U103/R103, 0) -> -0.047098402 | W103: =IF(U103>0, 1, 0) -> 0
A104: ORD_000103 | B104: CUST_01084 | C104: SKU_0059 | D104: HUB_03 | E104: 45664.524 | F104: 45664.53 | G104: DELIVERED | H104: 1 | I104: 50.51 | J104: 42.77 | K104: 0 | L104: 30 | M104: 37.48 | N104: 1.45 | O104: Cash on Delivery | P104: 0 | Q104: 5 | R104: =I104-K104 -> 50.51 | S104: =R104-J104 -> 7.74 | T104: =L104-M104 -> -7.48 | U104: =S104+T104-N104 -> -1.19 | V104: =IF(R104>0, U104/R104, 0) -> -0.023559691 | W104: =IF(U104>0, 1, 0) -> 0
A105: ORD_000104 | B105: CUST_00006 | C105: SKU_0119 | D105: HUB_13 | E105: 45664.598 | F105: 45664.606 | G105: DELIVERED | H105: 1 | I105: 138 | J105: 107.16 | K105: 13.8 | L105: 30 | M105: 51.76 | N105: 2.78 | O105: Debit Card | P105: 0 | Q105: 5 | R105: =I105-K105 -> 124.2 | S105: =R105-J105 -> 17.04 | T105: =L105-M105 -> -21.76 | U105: =S105+T105-N105 -> -7.5 | V105: =IF(R105>0, U105/R105, 0) -> -0.060386473 | W105: =IF(U105>0, 1, 0) -> 0
A106: ORD_000105 | B106: CUST_00982 | C106: SKU_0137 | D106: HUB_03 | E106: 45664.646 | F106: 45664.652 | G106: DELIVERED | H106: 1 | I106: 163.8 | J106: 133.49 | K106: 24.57 | L106: 30 | M106: 61.19 | N106: 3.05 | O106: UPI | P106: 0 | Q106: 5 | R106: =I106-K106 -> 139.23 | S106: =R106-J106 -> 5.74 | T106: =L106-M106 -> -31.19 | U106: =S106+T106-N106 -> -28.5 | V106: =IF(R106>0, U106/R106, 0) -> -0.20469726 | W106: =IF(U106>0, 1, 0) -> 0
A107: ORD_000106 | B107: CUST_00570 | C107: SKU_0140 | D107: HUB_02 | E107: 45664.682 | F107: 45664.689 | G107: DELIVERED | H107: 1 | I107: 287.56 | J107: 254.14 | K107: 0 | L107: 30 | M107: 54.78 | N107: 5.72 | O107: UPI | P107: 0 | Q107: 4 | R107: =I107-K107 -> 287.56 | S107: =R107-J107 -> 33.42 | T107: =L107-M107 -> -24.78 | U107: =S107+T107-N107 -> 2.92 | V107: =IF(R107>0, U107/R107, 0) -> 0.010154403 | W107: =IF(U107>0, 1, 0) -> 1
A108: ORD_000107 | B108: CUST_00407 | C108: SKU_0119 | D108: HUB_01 | E108: 45664.708 | F108: 45664.715 | G108: DELIVERED | H108: 1 | I108: 138 | J108: 107.16 | K108: 6.9 | L108: 30 | M108: 57.06 | N108: 2.9 | O108: UPI | P108: 0 | Q108: 4 | R108: =I108-K108 -> 131.1 | S108: =R108-J108 -> 23.94 | T108: =L108-M108 -> -27.06 | U108: =S108+T108-N108 -> -6.02 | V108: =IF(R108>0, U108/R108, 0) -> -0.045919146 | W108: =IF(U108>0, 1, 0) -> 0
A109: ORD_000108 | B109: CUST_00026 | C109: SKU_0041 | D109: HUB_04 | E109: 45664.759 | F109: 45664.765 | G109: DELIVERED | H109: 4 | I109: 669.4 | J109: 515.76 | K109: 0 | L109: 0 | M109: 41.18 | N109: 12.05 | O109: UPI | P109: 0 | Q109: 4 | R109: =I109-K109 -> 669.4 | S109: =R109-J109 -> 153.64 | T109: =L109-M109 -> -41.18 | U109: =S109+T109-N109 -> 100.41 | V109: =IF(R109>0, U109/R109, 0) -> 0.15 | W109: =IF(U109>0, 1, 0) -> 1
A110: ORD_000109 | B110: CUST_01029 | C110: SKU_0143 | D110: HUB_02 | E110: 45664.768 | F110: 45664.775 | G110: DELIVERED | H110: 2 | I110: 553.96 | J110: 400.64 | K110: 27.7 | L110: 0 | M110: 37.34 | N110: 9.47 | O110: Debit Card | P110: 0 | Q110: 5 | R110: =I110-K110 -> 526.26 | S110: =R110-J110 -> 125.62 | T110: =L110-M110 -> -37.34 | U110: =S110+T110-N110 -> 78.81 | V110: =IF(R110>0, U110/R110, 0) -> 0.14975487 | W110: =IF(U110>0, 1, 0) -> 1
A111: ORD_000110 | B111: CUST_00986 | C111: SKU_0066 | D111: HUB_14 | E111: 45664.814 | F111: 45664.821 | G111: RETURNED | H111: 1 | I111: 485.8 | J111: 312.58 | K111: 24.29 | L111: 0 | M111: 64.15 | N111: 8.31 | O111: Credit Card | P111: 0 | Q111: 1 | R111: =I111-K111 -> 461.51 | S111: =R111-J111 -> 148.93 | T111: =L111-M111 -> -64.15 | U111: =S111+T111-N111 -> 76.47 | V111: =IF(R111>0, U111/R111, 0) -> 0.16569522 | W111: =IF(U111>0, 1, 0) -> 1
A112: ORD_000111 | B112: CUST_00390 | C112: SKU_0075 | D112: HUB_14 | E112: 45664.829 | F112: 45664.84 | G112: DELIVERED | H112: 1 | I112: 567.99 | J112: 343.37 | K112: 28.4 | L112: 0 | M112: 36.81 | N112: 9.71 | O112: Credit Card | P112: 0 | Q112: 5 | R112: =I112-K112 -> 539.59 | S112: =R112-J112 -> 196.22 | T112: =L112-M112 -> -36.81 | U112: =S112+T112-N112 -> 149.7 | V112: =IF(R112>0, U112/R112, 0) -> 0.27743287 | W112: =IF(U112>0, 1, 0) -> 1
A113: ORD_000112 | B113: CUST_00710 | C113: SKU_0011 | D113: HUB_02 | E113: 45664.832 | G113: CANCELLED | H113: 2 | I113: 303.3 | J113: 211.62 | K113: 45.5 | L113: 30 | M113: 35.39 | N113: 0 | O113: Credit Card | P113: 8 | R113: =I113-K113 -> 257.8 | S113: =R113-J113 -> 46.18 | T113: =L113-M113 -> -5.39 | U113: =S113+T113-N113 -> 40.79 | V113: =IF(R113>0, U113/R113, 0) -> 0.15822343 | W113: =IF(U113>0, 1, 0) -> 1
A114: ORD_000113 | B114: CUST_00571 | C114: SKU_0008 | D114: HUB_13 | E114: 45664.847 | F114: 45664.856 | G114: DELIVERED | H114: 1 | I114: 87.73 | J114: 65.98 | K114: 4.39 | L114: 30 | M114: 41.48 | N114: 2.04 | O114: UPI | P114: 0 | Q114: 4 | R114: =I114-K114 -> 83.34 | S114: =R114-J114 -> 17.36 | T114: =L114-M114 -> -11.48 | U114: =S114+T114-N114 -> 3.84 | V114: =IF(R114>0, U114/R114, 0) -> 0.046076314 | W114: =IF(U114>0, 1, 0) -> 1
A115: ORD_000114 | B115: CUST_00754 | C115: SKU_0183 | D115: HUB_11 | E115: 45664.851 | F115: 45664.86 | G115: DELIVERED | H115: 1 | I115: 240.68 | J115: 159.28 | K115: 36.1 | L115: 30 | M115: 59.56 | N115: 4.22 | O115: UPI | P115: 0 | Q115: 5 | R115: =I115-K115 -> 204.58 | S115: =R115-J115 -> 45.3 | T115: =L115-M115 -> -29.56 | U115: =S115+T115-N115 -> 11.52 | V115: =IF(R115>0, U115/R115, 0) -> 0.05631049 | W115: =IF(U115>0, 1, 0) -> 1
A116: ORD_000115 | B116: CUST_00146 | C116: SKU_0224 | D116: HUB_11 | E116: 45664.904 | G116: CANCELLED | H116: 1 | I116: 401.31 | J116: 295.05 | K116: 60.2 | L116: 0 | M116: 40.64 | N116: 0 | O116: UPI | P116: 3 | R116: =I116-K116 -> 341.11 | S116: =R116-J116 -> 46.06 | T116: =L116-M116 -> -40.64 | U116: =S116+T116-N116 -> 5.42 | V116: =IF(R116>0, U116/R116, 0) -> 0.015889303 | W116: =IF(U116>0, 1, 0) -> 1
A117: ORD_000116 | B117: CUST_00785 | C117: SKU_0134 | D117: HUB_05 | E117: 45664.956 | F117: 45664.964 | G117: RETURNED | H117: 2 | I117: 76.26 | J117: 56.46 | K117: 7.63 | L117: 30 | M117: 38.14 | N117: 1.78 | O117: Cash on Delivery | P117: 0 | Q117: 1 | R117: =I117-K117 -> 68.63 | S117: =R117-J117 -> 12.17 | T117: =L117-M117 -> -8.14 | U117: =S117+T117-N117 -> 2.25 | V117: =IF(R117>0, U117/R117, 0) -> 0.032784497 | W117: =IF(U117>0, 1, 0) -> 1
A118: ORD_000117 | B118: CUST_00526 | C118: SKU_0181 | D118: HUB_04 | E118: 45665.27 | F118: 45665.279 | G118: DELIVERED | H118: 1 | I118: 149.33 | J118: 101.29 | K118: 22.4 | L118: 30 | M118: 41.26 | N118: 2.82 | O118: UPI | P118: 0 | Q118: 5 | R118: =I118-K118 -> 126.93 | S118: =R118-J118 -> 25.64 | T118: =L118-M118 -> -11.26 | U118: =S118+T118-N118 -> 11.56 | V118: =IF(R118>0, U118/R118, 0) -> 0.09107382 | W118: =IF(U118>0, 1, 0) -> 1
A119: ORD_000118 | B119: CUST_00013 | C119: SKU_0148 | D119: HUB_01 | E119: 45665.358 | F119: 45665.365 | G119: DELIVERED | H119: 1 | I119: 181.1 | J119: 115.87 | K119: 18.11 | L119: 30 | M119: 52.72 | N119: 3.47 | O119: Credit Card | P119: 0 | Q119: 5 | R119: =I119-K119 -> 162.99 | S119: =R119-J119 -> 47.12 | T119: =L119-M119 -> -22.72 | U119: =S119+T119-N119 -> 20.93 | V119: =IF(R119>0, U119/R119, 0) -> 0.12841279 | W119: =IF(U119>0, 1, 0) -> 1
A120: ORD_000119 | B120: CUST_00903 | C120: SKU_0167 | D120: HUB_15 | E120: 45665.381 | F120: 45665.4 | G120: DELIVERED | H120: 1 | I120: 100.77 | J120: 90.13 | K120: 5.04 | L120: 30 | M120: 50.83 | N120: 2.26 | O120: UPI | P120: 8 | Q120: 4 | R120: =I120-K120 -> 95.73 | S120: =R120-J120 -> 5.6 | T120: =L120-M120 -> -20.83 | U120: =S120+T120-N120 -> -17.49 | V120: =IF(R120>0, U120/R120, 0) -> -0.18270135 | W120: =IF(U120>0, 1, 0) -> 0
A121: ORD_000120 | B121: CUST_00384 | C121: SKU_0099 | D121: HUB_15 | E121: 45665.395 | F121: 45665.411 | G121: DELIVERED | H121: 1 | I121: 251.78 | J121: 208.99 | K121: 25.18 | L121: 30 | M121: 60.75 | N121: 4.62 | O121: Credit Card | P121: 4 | Q121: 3 | R121: =I121-K121 -> 226.6 | S121: =R121-J121 -> 17.61 | T121: =L121-M121 -> -30.75 | U121: =S121+T121-N121 -> -17.76 | V121: =IF(R121>0, U121/R121, 0) -> -0.078375993 | W121: =IF(U121>0, 1, 0) -> 0
A122: ORD_000121 | B122: CUST_00556 | C122: SKU_0072 | D122: HUB_09 | E122: 45665.411 | G122: CANCELLED | H122: 4 | I122: 1705.96 | J122: 1517.04 | K122: 85.3 | L122: 0 | M122: 57.81 | N122: 0 | O122: Credit Card | P122: 1 | R122: =I122-K122 -> 1620.66 | S122: =R122-J122 -> 103.62 | T122: =L122-M122 -> -57.81 | U122: =S122+T122-N122 -> 45.81 | V122: =IF(R122>0, U122/R122, 0) -> 0.028266262 | W122: =IF(U122>0, 1, 0) -> 1
A123: ORD_000122 | B123: CUST_00887 | C123: SKU_0242 | D123: HUB_14 | E123: 45665.506 | F123: 45665.524 | G123: DELIVERED | H123: 2 | I123: 1397.76 | J123: 1179.38 | K123: 349.44 | L123: 0 | M123: 44.35 | N123: 18.87 | O123: UPI | P123: 11 | Q123: 1 | R123: =I123-K123 -> 1048.32 | S123: =R123-J123 -> -131.06 | T123: =L123-M123 -> -44.35 | U123: =S123+T123-N123 -> -194.28 | V123: =IF(R123>0, U123/R123, 0) -> -0.18532509 | W123: =IF(U123>0, 1, 0) -> 0
A124: ORD_000123 | B124: CUST_00019 | C124: SKU_0113 | D124: HUB_04 | E124: 45665.624 | F124: 45665.638 | G124: DELIVERED | H124: 1 | I124: 36.9 | J124: 28.25 | K124: 9.22 | L124: 30 | M124: 48.62 | N124: 1.04 | O124: UPI | P124: 5 | Q124: 3 | R124: =I124-K124 -> 27.68 | S124: =R124-J124 -> -0.57 | T124: =L124-M124 -> -18.62 | U124: =S124+T124-N124 -> -20.23 | V124: =IF(R124>0, U124/R124, 0) -> -0.7308526 | W124: =IF(U124>0, 1, 0) -> 0
A125: ORD_000124 | B125: CUST_00575 | C125: SKU_0107 | D125: HUB_05 | E125: 45665.651 | F125: 45665.666 | G125: DELIVERED | H125: 1 | I125: 100.7 | J125: 68.26 | K125: 10.07 | L125: 30 | M125: 39.62 | N125: 2.17 | O125: Net Banking | P125: 1 | Q125: 3 | R125: =I125-K125 -> 90.63 | S125: =R125-J125 -> 22.37 | T125: =L125-M125 -> -9.62 | U125: =S125+T125-N125 -> 10.58 | V125: =IF(R125>0, U125/R125, 0) -> 0.11673839 | W125: =IF(U125>0, 1, 0) -> 1
A126: ORD_000125 | B126: CUST_00751 | C126: SKU_0034 | D126: HUB_07 | E126: 45665.717 | F126: 45665.73 | G126: DELIVERED | H126: 2 | I126: 269.54 | J126: 193.44 | K126: 13.48 | L126: 30 | M126: 50.14 | N126: 5.15 | O126: Debit Card | P126: 3 | Q126: 4 | R126: =I126-K126 -> 256.06 | S126: =R126-J126 -> 62.62 | T126: =L126-M126 -> -20.14 | U126: =S126+T126-N126 -> 37.33 | V126: =IF(R126>0, U126/R126, 0) -> 0.14578614 | W126: =IF(U126>0, 1, 0) -> 1
A127: ORD_000126 | B127: CUST_01004 | C127: SKU_0057 | D127: HUB_02 | E127: 45665.804 | G127: CANCELLED | H127: 1 | I127: 224.45 | J127: 155.32 | K127: 11.22 | L127: 30 | M127: 62.42 | N127: 0 | O127: UPI | P127: 6 | R127: =I127-K127 -> 213.23 | S127: =R127-J127 -> 57.91 | T127: =L127-M127 -> -32.42 | U127: =S127+T127-N127 -> 25.49 | V127: =IF(R127>0, U127/R127, 0) -> 0.11954228 | W127: =IF(U127>0, 1, 0) -> 1
A128: ORD_000127 | B128: CUST_00419 | C128: SKU_0117 | D128: HUB_08 | E128: 45665.809 | F128: 45665.826 | G128: DELIVERED | H128: 3 | I128: 1599.51 | J128: 915.81 | K128: 399.88 | L128: 0 | M128: 41.56 | N128: 21.59 | O128: Debit Card | P128: 4 | Q128: 4 | R128: =I128-K128 -> 1199.63 | S128: =R128-J128 -> 283.82 | T128: =L128-M128 -> -41.56 | U128: =S128+T128-N128 -> 220.67 | V128: =IF(R128>0, U128/R128, 0) -> 0.18394838 | W128: =IF(U128>0, 1, 0) -> 1
A129: ORD_000128 | B129: CUST_00419 | C129: SKU_0120 | D129: HUB_11 | E129: 45665.952 | F129: 45665.969 | G129: DELIVERED | H129: 2 | I129: 443.92 | J129: 316.96 | K129: 22.2 | L129: 0 | M129: 45.91 | N129: 7.59 | O129: UPI | P129: 5 | Q129: 4 | R129: =I129-K129 -> 421.72 | S129: =R129-J129 -> 104.76 | T129: =L129-M129 -> -45.91 | U129: =S129+T129-N129 -> 51.26 | V129: =IF(R129>0, U129/R129, 0) -> 0.12154984 | W129: =IF(U129>0, 1, 0) -> 1
A130: ORD_000129 | B130: CUST_00122 | C130: SKU_0147 | D130: HUB_02 | E130: 45666.359 | F130: 45666.368 | G130: RETURNED | H130: 1 | I130: 270.26 | J130: 196.9 | K130: 13.51 | L130: 30 | M130: 64.25 | N130: 5.16 | O130: UPI | P130: 0 | Q130: 2 | R130: =I130-K130 -> 256.75 | S130: =R130-J130 -> 59.85 | T130: =L130-M130 -> -34.25 | U130: =S130+T130-N130 -> 20.44 | V130: =IF(R130>0, U130/R130, 0) -> 0.079610516 | W130: =IF(U130>0, 1, 0) -> 1
A131: ORD_000130 | B131: CUST_00432 | C131: SKU_0071 | D131: HUB_11 | E131: 45666.433 | F131: 45666.444 | G131: DELIVERED | H131: 4 | I131: 617.48 | J131: 453.6 | K131: 92.62 | L131: 0 | M131: 61.04 | N131: 9.45 | O131: UPI | P131: 0 | Q131: 5 | R131: =I131-K131 -> 524.86 | S131: =R131-J131 -> 71.26 | T131: =L131-M131 -> -61.04 | U131: =S131+T131-N131 -> 0.77 | V131: =IF(R131>0, U131/R131, 0) -> 0.0014670579 | W131: =IF(U131>0, 1, 0) -> 1
A132: ORD_000131 | B132: CUST_00044 | C132: SKU_0159 | D132: HUB_10 | E132: 45666.525 | F132: 45666.537 | G132: DELIVERED | H132: 1 | I132: 70.42 | J132: 58.49 | K132: 17.6 | L132: 30 | M132: 50.4 | N132: 1.49 | O132: Credit Card | P132: 2 | Q132: 4 | R132: =I132-K132 -> 52.82 | S132: =R132-J132 -> -5.67 | T132: =L132-M132 -> -20.4 | U132: =S132+T132-N132 -> -27.56 | V132: =IF(R132>0, U132/R132, 0) -> -0.52177206 | W132: =IF(U132>0, 1, 0) -> 0
A133: ORD_000132 | B133: CUST_00381 | C133: SKU_0210 | D133: HUB_05 | E133: 45666.529 | F133: 45666.546 | G133: DELIVERED | H133: 1 | I133: 100.15 | J133: 78.53 | K133: 0 | L133: 30 | M133: 58.4 | N133: 2.34 | O133: UPI | P133: 4 | Q133: 4 | R133: =I133-K133 -> 100.15 | S133: =R133-J133 -> 21.62 | T133: =L133-M133 -> -28.4 | U133: =S133+T133-N133 -> -9.12 | V133: =IF(R133>0, U133/R133, 0) -> -0.091063405 | W133: =IF(U133>0, 1, 0) -> 0
A134: ORD_000133 | B134: CUST_00145 | C134: SKU_0040 | D134: HUB_13 | E134: 45666.545 | G134: CANCELLED | H134: 2 | I134: 473.9 | J134: 390 | K134: 0 | L134: 0 | M134: 40.64 | N134: 0 | O134: UPI | P134: 15 | R134: =I134-K134 -> 473.9 | S134: =R134-J134 -> 83.9 | T134: =L134-M134 -> -40.64 | U134: =S134+T134-N134 -> 43.26 | V134: =IF(R134>0, U134/R134, 0) -> 0.091285081 | W134: =IF(U134>0, 1, 0) -> 1
A135: ORD_000134 | B135: CUST_00363 | C135: SKU_0142 | D135: HUB_12 | E135: 45666.614 | F135: 45666.629 | G135: DELIVERED | H135: 3 | I135: 1946.04 | J135: 1676.19 | K135: 97.3 | L135: 0 | M135: 43.34 | N135: 33.28 | O135: Credit Card | P135: 2 | Q135: 3 | R135: =I135-K135 -> 1848.74 | S135: =R135-J135 -> 172.55 | T135: =L135-M135 -> -43.34 | U135: =S135+T135-N135 -> 95.93 | V135: =IF(R135>0, U135/R135, 0) -> 0.051889395 | W135: =IF(U135>0, 1, 0) -> 1
A136: ORD_000135 | B136: CUST_01074 | C136: SKU_0103 | D136: HUB_02 | E136: 45666.614 | F136: 45666.631 | G136: DELIVERED | H136: 2 | I136: 407.22 | J136: 295.5 | K136: 0 | L136: 0 | M136: 39.93 | N136: 7.33 | O136: UPI | P136: 9 | Q136: 4 | R136: =I136-K136 -> 407.22 | S136: =R136-J136 -> 111.72 | T136: =L136-M136 -> -39.93 | U136: =S136+T136-N136 -> 64.46 | V136: =IF(R136>0, U136/R136, 0) -> 0.15829281 | W136: =IF(U136>0, 1, 0) -> 1
A137: ORD_000136 | B137: CUST_01089 | C137: SKU_0124 | D137: HUB_02 | E137: 45666.658 | F137: 45666.665 | G137: DELIVERED | H137: 2 | I137: 116.06 | J137: 95.62 | K137: 5.8 | L137: 30 | M137: 44.21 | N137: 2.52 | O137: Net Banking | P137: 0 | Q137: 4 | R137: =I137-K137 -> 110.26 | S137: =R137-J137 -> 14.64 | T137: =L137-M137 -> -14.21 | U137: =S137+T137-N137 -> -2.09 | V137: =IF(R137>0, U137/R137, 0) -> -0.018955197 | W137: =IF(U137>0, 1, 0) -> 0
A138: ORD_000137 | B138: CUST_00355 | C138: SKU_0245 | D138: HUB_04 | E138: 45666.696 | G138: CANCELLED | H138: 1 | I138: 708.56 | J138: 613.49 | K138: 70.86 | L138: 0 | M138: 61.09 | N138: 0 | O138: UPI | P138: 11 | R138: =I138-K138 -> 637.7 | S138: =R138-J138 -> 24.21 | T138: =L138-M138 -> -61.09 | U138: =S138+T138-N138 -> -36.88 | V138: =IF(R138>0, U138/R138, 0) -> -0.057832837 | W138: =IF(U138>0, 1, 0) -> 0
A139: ORD_000138 | B139: CUST_00800 | C139: SKU_0123 | D139: HUB_04 | E139: 45666.778 | F139: 45666.784 | G139: DELIVERED | H139: 2 | I139: 433.88 | J139: 378.32 | K139: 0 | L139: 0 | M139: 54.45 | N139: 7.81 | O139: UPI | P139: 0 | Q139: 5 | R139: =I139-K139 -> 433.88 | S139: =R139-J139 -> 55.56 | T139: =L139-M139 -> -54.45 | U139: =S139+T139-N139 -> -6.7 | V139: =IF(R139>0, U139/R139, 0) -> -0.015442058 | W139: =IF(U139>0, 1, 0) -> 0
A140: ORD_000139 | B140: CUST_01188 | C140: SKU_0100 | D140: HUB_13 | E140: 45666.943 | F140: 45666.97 | G140: DELIVERED | H140: 1 | I140: 50.65 | J140: 42.86 | K140: 2.53 | L140: 30 | M140: 39.42 | N140: 1.41 | O140: UPI | P140: 19 | Q140: 1 | R140: =I140-K140 -> 48.12 | S140: =R140-J140 -> 5.26 | T140: =L140-M140 -> -9.42 | U140: =S140+T140-N140 -> -5.57 | V140: =IF(R140>0, U140/R140, 0) -> -0.11575229 | W140: =IF(U140>0, 1, 0) -> 0
A141: ORD_000140 | B141: CUST_01165 | C141: SKU_0209 | D141: HUB_08 | E141: 45667.254 | F141: 45667.274 | G141: DELIVERED | H141: 2 | I141: 346.64 | J141: 307.24 | K141: 86.66 | L141: 30 | M141: 61.29 | N141: 5.22 | O141: Credit Card | P141: 8 | Q141: 3 | R141: =I141-K141 -> 259.98 | S141: =R141-J141 -> -47.26 | T141: =L141-M141 -> -31.29 | U141: =S141+T141-N141 -> -83.77 | V141: =IF(R141>0, U141/R141, 0) -> -0.32221709 | W141: =IF(U141>0, 1, 0) -> 0
A142: ORD_000141 | B142: CUST_00826 | C142: SKU_0165 | D142: HUB_13 | E142: 45667.341 | F142: 45667.349 | G142: DELIVERED | H142: 1 | I142: 234.49 | J142: 139.73 | K142: 23.45 | L142: 30 | M142: 57.35 | N142: 4.34 | O142: Debit Card | P142: 0 | Q142: 5 | R142: =I142-K142 -> 211.04 | S142: =R142-J142 -> 71.31 | T142: =L142-M142 -> -27.35 | U142: =S142+T142-N142 -> 39.62 | V142: =IF(R142>0, U142/R142, 0) -> 0.18773692 | W142: =IF(U142>0, 1, 0) -> 1
A143: ORD_000142 | B143: CUST_01152 | C143: SKU_0172 | D143: HUB_06 | E143: 45667.408 | F143: 45667.42 | G143: DELIVERED | H143: 1 | I143: 450.95 | J143: 385.74 | K143: 67.64 | L143: 0 | M143: 42.22 | N143: 6.9 | O143: UPI | P143: 0 | Q143: 5 | R143: =I143-K143 -> 383.31 | S143: =R143-J143 -> -2.43 | T143: =L143-M143 -> -42.22 | U143: =S143+T143-N143 -> -51.55 | V143: =IF(R143>0, U143/R143, 0) -> -0.13448645 | W143: =IF(U143>0, 1, 0) -> 0
A144: ORD_000143 | B144: CUST_00398 | C144: SKU_0137 | D144: HUB_10 | E144: 45667.454 | F144: 45667.468 | G144: DELIVERED | H144: 4 | I144: 655.2 | J144: 533.96 | K144: 98.28 | L144: 0 | M144: 61.82 | N144: 10.02 | O144: UPI | P144: 5 | Q144: 3 | R144: =I144-K144 -> 556.92 | S144: =R144-J144 -> 22.96 | T144: =L144-M144 -> -61.82 | U144: =S144+T144-N144 -> -48.88 | V144: =IF(R144>0, U144/R144, 0) -> -0.087768441 | W144: =IF(U144>0, 1, 0) -> 0
A145: ORD_000144 | B145: CUST_00880 | C145: SKU_0058 | D145: HUB_08 | E145: 45667.522 | F145: 45667.545 | G145: DELIVERED | H145: 1 | I145: 30.57 | J145: 24.48 | K145: 1.53 | L145: 30 | M145: 40.61 | N145: 1.06 | O145: UPI | P145: 13 | Q145: 1 | R145: =I145-K145 -> 29.04 | S145: =R145-J145 -> 4.56 | T145: =L145-M145 -> -10.61 | U145: =S145+T145-N145 -> -7.11 | V145: =IF(R145>0, U145/R145, 0) -> -0.24483471 | W145: =IF(U145>0, 1, 0) -> 0
A146: ORD_000145 | B146: CUST_00463 | C146: SKU_0148 | D146: HUB_13 | E146: 45667.607 | F146: 45667.626 | G146: DELIVERED | H146: 1 | I146: 181.1 | J146: 115.87 | K146: 27.16 | L146: 30 | M146: 35.86 | N146: 3.31 | O146: UPI | P146: 7 | Q146: 3 | R146: =I146-K146 -> 153.94 | S146: =R146-J146 -> 38.07 | T146: =L146-M146 -> -5.86 | U146: =S146+T146-N146 -> 28.9 | V146: =IF(R146>0, U146/R146, 0) -> 0.18773548 | W146: =IF(U146>0, 1, 0) -> 1
...

Sheet executive_scenario_model
B2: URBANCART: EXECUTIVE UNIT ECONOMICS & SCENARIO ENGINE
B4: Baseline Portfolio KPIs (Actual 7,000 Orders) | F4: Free-Delivery Threshold Sensitivity Simulation
B5: Total Gross Merchandise Value (GMV) | C5: =SUM(fact_orders!I2:I7001) -> 3994696.6 | F5: Min Basket Size for Free Delivery | G5: Projected Delivery Fee Recovery | H5: Net CM2 Realization | I5: Margin Expansion
B6: Total Promo Discounts Burned | C6: =SUM(fact_orders!K2:K7001) -> 289736.79 | F6: Threshold ₹299 | G6: =C11*1.25 -> -301799.44 | H6: =C13+(G6-C11) -> 391363.52 | I6: =(H6-C13)/C13 -> -0.13362134
B7: Discount Burn Rate (%) | C7: =C6/C5 -> 0.072530361 | F7: Threshold ₹349 | G7: =C11*1.15 -> -277655.48 | H7: =C13+(G7-C11) -> 415507.48 | I7: =(H7-C13)/C13 -> -0.080172804
B8: Net Sales | C8: =SUM(fact_orders!R2:R7001) -> 3704959.9 | F8: Threshold ₹399 | G8: =C11*1 -> -241439.55 | H8: =C13+(G8-C11) -> 451723.41 | I8: =(H8-C13)/C13 -> 0
B9: Total Direct Product Cost (COGS) | C9: =SUM(fact_orders!J2:J7001) -> 2946745.2 | F9: Threshold ₹449 | G9: =C11*0.88 -> -212466.8 | H9: =C13+(G9-C11) -> 480696.16 | I9: =(H9-C13)/C13 -> 0.064138243
B10: Gross Contribution Margin 1 (CM1) | C10: =SUM(fact_orders!S2:S7001) -> 758214.69 | F10: Threshold ₹499 | G10: =C11*0.76 -> -183494.06 | H10: =C13+(G10-C11) -> 509668.9 | I10: =(H10-C13)/C13 -> 0.12827649
B11: Net Logistics Deficit (Delivery Burn) | C11: =SUM(fact_orders!T2:T7001) -> -241439.55
B12: Total Payment Gateway Fees | C12: =SUM(fact_orders!N2:N7001) -> 65051.73
B13: Net Contribution Margin 2 (CM2) | C13: =SUM(fact_orders!U2:U7001) -> 451723.41
B14: Portfolio CM2 Margin (%) | C14: =C13/C8 -> 0.12192397
B15: Order Success Rate (Delivered vs Total) | C15: =COUNTIF(fact_orders!G2:G7001, "DELIVERED")/COUNTA(fact_orders!G2:G7001) -> 0.87014286
B16: Return Leakage Rate | C16: =COUNTIF(fact_orders!G2:G7001, "RETURNED")/COUNTA(fact_orders!G2:G7001) -> 0.078571429
B17: Profitable Order Proportion | C17: =AVERAGE(fact_orders!W2:W7001) -> 0.66685714
